.DS_Store
unfollow/__init__.py
unfollow/beautify.py
unfollow/cli.py
unfollow/config.py
unfollow/input.py
unfollow/unfollow.py
unfollow-5.0.1.dist-info/LICENSE
unfollow-5.0.1.dist-info/METADATA
unfollow-5.0.1.dist-info/WHEEL
unfollow-5.0.1.dist-info/entry_points.txt
unfollow-5.0.1.dist-info/top_level.txt
unfollow-5.0.1.dist-info/RECORD
