Metadata-Version: 2.1
Name: unfollow
Version: 5.0.1
Summary: 😡 Python CLI tool that shows you who has unfollowed you on GitHub
Home-page: https://github.com/TechWiz-3/who-unfollowed-me
Author: Zac the Wise aka TechWiz-3
Classifier: Development Status :: 5 - Production/Stable
Classifier: Environment :: Console
Classifier: Environment :: Console :: Curses
Classifier: Intended Audience :: Developers
Classifier: Operating System :: Microsoft :: Windows
Classifier: License :: OSI Approved :: GNU General Public License v3 or later (GPLv3+)
Classifier: Operating System :: POSIX :: Linux
Classifier: Programming Language :: Python :: 3
Classifier: Topic :: Utilities
License-File: LICENSE
Requires-Dist: rich
